decall_project/__init__.py
decall-0.1.dist-info/LICENSE.txt
decall-0.1.dist-info/METADATA
decall-0.1.dist-info/WHEEL
decall-0.1.dist-info/top_level.txt
decall-0.1.dist-info/RECORD
