Metadata-Version: 2.1
Name: decall
Version: 0.1
Summary: This is a python-package to access month,  year and with mathamatical functions called xmath
Home-page: UNKNOWN
Author: Abul Aiman Shaa
Author-email: shaaimanaalik@gmail.com
License: UNKNOWN
Platform: UNKNOWN
Classifier: Programming Language :: Python :: 3
Classifier: License :: OSI Approved :: MIT License
Classifier: Operating System :: OS Independent
